<?xml version="1.0" encoding="utf-8"?>
<m_1025_1_Mysterio001>
	<name>
	</name>
	<description>Mysterio has escaped from prison and is… well, I'm not sure what he's doing!  That's the problem with Mysterio – you never know what he's up to until it's too late! I mean, it's in his name and everything! We'd better head to Villainville to stop whatever it is he’s up to.</description>
	<mission_briefing_speaker>spider_man_black</mission_briefing_speaker>
	<map>
		<x>78</x>
		<y>170</y>
	</map>
	<target_level>1</target_level>
	<stages>
		<stage>
			<stage_number>1</stage_number>
			<scenario_bundle>SHC_Subway_M025_S01_scenario</scenario_bundle>
		</stage>
		<stage>
			<stage_number>2</stage_number>
			<scenario_bundle>Factory_M025_S02_scenario</scenario_bundle>
		</stage>
		<stage>
			<stage_number>3</stage_number>
			<scenario_bundle>Factory_M025_S03_BOSS_scenario</scenario_bundle>
		</stage>
	</stages>
	<rating>
		<bronze>
			<score_needed>
				<player>0</player>
				<player>0</player>
				<player>0</player>
				<player>0</player>
			</score_needed>
		</bronze>
		<silver>
			<score_needed>
				<player>12624</player>
				<player>19864</player>
				<player>29332</player>
				<player>34902</player>
			</score_needed>
		</silver>
		<gold>
			<score_needed>
				<player>26860</player>
				<player>42265</player>
				<player>62410</player>
				<player>74260</player>
			</score_needed>
		</gold>
		<adamantium>
			<score_needed>
				<player>34000</player>
				<player>53500</player>
				<player>79000</player>
				<player>94000</player>
			</score_needed>
		</adamantium>
	</rating>
	<awards>
		<bronze>
			<lootTableIDs>1007,101</lootTableIDs>
		</bronze>
		<silver>
			<lootTableIDs>1007,101</lootTableIDs>
		</silver>
		<gold>
			<lootTableIDs>1007,101</lootTableIDs>
		</gold>
		<adamantium>
			<lootTableIDs>1007,110,101</lootTableIDs>
		</adamantium>
	</awards>
</m_1025_1_Mysterio001>